gau/__init__.py
gau/cli.py
gau/output.py
gau/runner.py
gau/providers/__init__.py
gau/providers/base.py
gau/providers/commoncrawl.py
gau/providers/otx.py
gau/providers/urlscan.py
gau/providers/wayback.py
gau_python_next-2.3.0.dist-info/licenses/LICENSE
gau_python_next-2.3.0.dist-info/METADATA
gau_python_next-2.3.0.dist-info/WHEEL
gau_python_next-2.3.0.dist-info/entry_points.txt
gau_python_next-2.3.0.dist-info/top_level.txt
gau_python_next-2.3.0.dist-info/RECORD
