Metadata-Version: 2.4
Name: gau-python-next
Version: 2.3.0
Summary: A Python tool to fetch known URLs from AlienVault, Wayback Machine, Common Crawl, and URLScan.
Author-email: H3xano <h3xano@gmail.com>
Project-URL: Homepage, https://github.com/H3xano/gau-python
Project-URL: Bug Tracker, https://github.com/H3xano/gau-python/issues
Keywords: recon,bug bounty,urls,gau,security
Classifier: Programming Language :: Python :: 3
Classifier: License :: OSI Approved :: MIT License
Classifier: Operating System :: OS Independent
Classifier: Topic :: Internet :: WWW/HTTP
Classifier: Topic :: Security
Classifier: Topic :: Utilities
Requires-Python: >=3.8
License-File: LICENSE
Requires-Dist: httpx[http2]
Requires-Dist: tomli
Requires-Dist: loguru
Requires-Dist: aiofiles
Dynamic: license-file
